opsinpy/__init__.py
opsinpy/exceptions.py
opsinpy/opsin-cli-2.8.0-jar-with-dependencies.jar
opsinpy/opsinpy.py
opsinpy-0.1.0.dist-info/licenses/AUTHORS
opsinpy-0.1.0.dist-info/licenses/LICENSE
opsinpy-0.1.0.dist-info/METADATA
opsinpy-0.1.0.dist-info/WHEEL
opsinpy-0.1.0.dist-info/top_level.txt
opsinpy-0.1.0.dist-info/RECORD
