Metadata-Version: 2.4
Name: opsinpy
Version: 0.1.0
Summary: Python bindings for OPSIN (Open Parser for Systematic IUPAC Nomenclature)
Author-email: Charlles Abreu <craabreu@gmail.com>
Maintainer-email: Charlles Abreu <craabreu@gmail.com>
License: MIT
Project-URL: Homepage, https://github.com/craabreu/opsinpy
Project-URL: Bug Reports, https://github.com/craabreu/opsinpy/issues
Project-URL: Source, https://github.com/craabreu/opsinpy
Project-URL: Documentation, https://opsin.ch.cam.ac.uk/
Keywords: chemistry,cheminformatics,iupac,nomenclature,opsin
Classifier: Development Status :: 4 - Beta
Classifier: Intended Audience :: Science/Research
Classifier: Natural Language :: English
Classifier: Operating System :: OS Independent
Classifier: Programming Language :: Python :: 3
Classifier: Programming Language :: Python :: 3.8
Classifier: Programming Language :: Python :: 3.9
Classifier: Programming Language :: Python :: 3.10
Classifier: Programming Language :: Python :: 3.11
Classifier: Programming Language :: Python :: 3.12
Classifier: Topic :: Scientific/Engineering :: Chemistry
Requires-Python: >=3.8
License-File: LICENSE
License-File: AUTHORS
Requires-Dist: JPype1<2.0,>=1.4.0
Requires-Dist: typing-extensions>=3.7.4; python_version < "3.8"
Provides-Extra: dev
Requires-Dist: pytest>=6.0; extra == "dev"
Requires-Dist: pytest-cov>=4.0; extra == "dev"
Requires-Dist: coverage[toml]>=7.0; extra == "dev"
Requires-Dist: black>=21.0; extra == "dev"
Requires-Dist: ruff>=0.3.0; extra == "dev"
Requires-Dist: mypy>=0.900; extra == "dev"
Requires-Dist: build>=0.7.0; extra == "dev"
Requires-Dist: twine>=4.0.0; extra == "dev"
Dynamic: license-file
